<REF_I12 xmlns="urn:hl7-org:v2xml">
<MSH>
    <MSH.1>|</MSH.1>
    <MSH.2>^~\&amp;</MSH.2>
    <MSH.3>
      <HD.1>eDischargeSummary.Healthlink.5</HD.1>
    </MSH.3>
    <MSH.4>
      <HD.1>St. Vincent&apos;s University Hospital LIVE</HD.1>
      <HD.2>910</HD.2>
      <HD.3>DOH</HD.3>
    </MSH.4>
<MSH.6>
      <HD.1>Hlink,Doctor</HD.1>
      <HD.2>012121.5013</HD.2>
      <HD.3>MCN.HLPracticeID</HD.3>
    </MSH.6>
 <MSH.7>
      <TS.1>20241118023530</TS.1>
    </MSH.7>
    <MSH.9>
      <MSG.1>REF</MSG.1>
      <MSG.2>I12</MSG.2>
      <MSG.3>REF_I12</MSG.3>
    </MSH.9>
    <MSH.10>282793</MSH.10>
    <MSH.11>
      <PT.1>P</PT.1>
    </MSH.11>
    <MSH.12>
      <VID.1>2.4</VID.1>
    </MSH.12>
  </MSH>
 <REF_I12.PROVIDER_CONTACT> 
    <PRD> 
      <PRD.1> 
        <CE.1>PP</CE.1>
        <CE.2>Primary Care Provider</CE.2> 
        <CE.3>HL70286</CE.3> 
      </PRD.1> 
      <PRD.2> 
        <XPN.1> 
          <FN.1>Hlink</FN.1> 
        </XPN.1> 
        <XPN.2>Doctor</XPN.2> 
        <XPN.5>DR.</XPN.5> 
      </PRD.2> 
 <PRD.3> 
        <XAD.1><SAD.1>GP TEST practice name</SAD.1></XAD.1>
        <XAD.2>GP TEST Street name</XAD.2>
        <XAD.3>GP Town name</XAD.3>
        <XAD.4>GP County name</XAD.4>
      </PRD.3> 
 <PRD.4>
        <PL.9>GP TEST some ficticious location</PL.9>
      </PRD.4>
      <PRD.7>
        <PI.1>012121</PI.1> 
      </PRD.7>
    </PRD> 
  </REF_I12.PROVIDER_CONTACT>
<PID> 
    <PID.3> 
      <CX.1>1119085</CX.1> 
      <CX.4> 
        <HD.1>SVUH</HD.1> 
      </CX.4> 
      <CX.5>MRN</CX.5> 
      <CX.6> 
        <HD.1>SVUH</HD.1> 
      </CX.6> 
    </PID.3> 
    <PID.5> 
      <XPN.1> 
        <FN.1>ARATO</FN.1> 
      </XPN.1> 
      <XPN.2>Patrick</XPN.2> 
    </PID.5> 
    <PID.7> 
      <TS.1>19440708</TS.1> 
    </PID.7> 
    <PID.8>F</PID.8> 
    <PID.11> 
      <XAD.1> 
        <SAD.1>location 1</SAD.1> 
      </XAD.1> 
      <XAD.2>location 2</XAD.2> 
      <XAD.3>COUNTY CARLOW  </XAD.3> 
    </PID.11> 
    <PID.13> 
      <XTN.1>H:UNK, M:0873328704, W:.</XTN.1> 
    </PID.13> 
    <PID.29></PID.29> 
    <PID.30></PID.30> 
  </PID>
 <DG1> 
    <DG1.1>1</DG1.1> 
    <DG1.2></DG1.2> 
    <DG1.3> 
      <CE.1></CE.1> 
      <CE.2>Primary Diagnosis (Free Text)</CE.2> 
      <CE.3></CE.3> 
    </DG1.3> 
    <DG1.4>Primary Diagnosis (Free Text) cb test</DG1.4> 
    <DG1.6>W</DG1.6> 
    <DG1.16> 
      <XCN.2> 
        <FN.1>HURLEY</FN.1> 
      </XCN.2> 
      <XCN.3>HILARY</XCN.3> 
      <XCN.6>DR.</XCN.6> 
    </DG1.16> 
  </DG1>
 <DG1> 
    <DG1.1>2</DG1.1> 
    <DG1.2></DG1.2> 
    <DG1.3> 
      <CE.1></CE.1> 
      <CE.2>Diagnosis Extras(Free Text)</CE.2> 
      <CE.3></CE.3> 
    </DG1.3> 
    <DG1.4>Additional Diagnosis (Free Text) cb test</DG1.4> 
    <DG1.6>W</DG1.6> 
    <DG1.16> 
      <XCN.2> 
        <FN.1>HURLEY</FN.1> 
      </XCN.2> 
      <XCN.3>HILARY</XCN.3> 
      <XCN.6>DR.</XCN.6> 
    </DG1.16> 
  </DG1>
<REF_I12.PROCEDURE> 
    <PR1> 
      <PR1.1>1</PR1.1> 
      <PR1.2></PR1.2> 
      <PR1.3> 
        <CE.1></CE.1> 
        <CE.2>Primary Procedure (Free Text):Principle Procedure/Intervention (Free Text) cb test; Procedure Date Below:</CE.2> 
        <CE.3></CE.3> 
      </PR1.3> 
      <PR1.5> 
        <TS.1>20241118000000</TS.1> 
      </PR1.5> 
    </PR1> 
  </REF_I12.PROCEDURE>
<REF_I12.PROCEDURE> 
    <PR1> 
      <PR1.1>2</PR1.1> 
      <PR1.2></PR1.2> 
      <PR1.3> 
        <CE.1></CE.1> 
        <CE.2>Other Procedures (Free Text) :Other Procedure (Free Text)  cb test; UNKNOWN PROCEDURE DATE:</CE.2> 
        <CE.3></CE.3> 
      </PR1.3> 
      <PR1.5> 
        <TS.1>20241118000000</TS.1> 
      </PR1.5> 
    </PR1> 
  </REF_I12.PROCEDURE>
<REF_I12.OBSERVATION> 
    <OBR> 
      <OBR.1>1</OBR.1> 
      <OBR.2> 
          <EI.1></EI.1>
	      <EI.2></EI.2>
	      <EI.3></EI.3> 
	      <EI.4></EI.4> 
      </OBR.2>
      <OBR.3> 
          <EI.1>282793</EI.1> 
      </OBR.3> 
      <OBR.4> 
          <CE.1></CE.1> 
          <CE.2>Reason for Admission</CE.2> 
          <CE.3></CE.3> 
      </OBR.4> 
      <OBR.7> 
          <TS.1>20241118143530</TS.1> 
      </OBR.7> 
      <OBR.25></OBR.25> 
    </OBR> 
<REF_I12.RESULTS_NOTES> 
      <OBX> 
        <OBX.1>1</OBX.1> 
        <OBX.2>FT</OBX.2> 
        <OBX.3> 
          <CE.1></CE.1> 
          <CE.2>Reason For Admission (Free Text)  cb test</CE.2> 
          <CE.3>L</CE.3> 
        </OBX.3> 
        <OBX.5></OBX.5> 
        <OBX.11>F</OBX.11> 
        <OBX.14> 
          <TS.1></TS.1> 
        </OBX.14> 
      </OBX> 
    </REF_I12.RESULTS_NOTES> 
  </REF_I12.OBSERVATION>
<REF_I12.OBSERVATION> 
    <OBR> 
      <OBR.1>2</OBR.1> 
      <OBR.2> 
          <EI.1></EI.1>
	      <EI.2></EI.2>
	      <EI.3></EI.3> 
	      <EI.4></EI.4> 
      </OBR.2>
      <OBR.3> 
          <EI.1>282793</EI.1> 
      </OBR.3> 
      <OBR.4> 
          <CE.1></CE.1> 
          <CE.2>Infection Control - CPE</CE.2> 
          <CE.3></CE.3> 
      </OBR.4> 
      <OBR.7> 
          <TS.1>20241118143530</TS.1> 
      </OBR.7> 
      <OBR.25></OBR.25> 
    </OBR> 
<REF_I12.RESULTS_NOTES> 
      <OBX> 
        <OBX.1>2</OBX.1> 
        <OBX.2></OBX.2> 
        <OBX.3> 
          <CE.1></CE.1> 
          <CE.2>Yes</CE.2> 
          <CE.3>L</CE.3> 
        </OBX.3> 
        <OBX.5></OBX.5> 
        <OBX.11>F</OBX.11> 
        <OBX.14> 
          <TS.1></TS.1> 
        </OBX.14> 
      </OBX> 
    </REF_I12.RESULTS_NOTES> 
  </REF_I12.OBSERVATION>
<REF_I12.OBSERVATION> 
    <OBR> 
      <OBR.1>3</OBR.1> 
      <OBR.2> 
          <EI.1></EI.1>
	      <EI.2></EI.2>
	      <EI.3></EI.3> 
	      <EI.4></EI.4> 
      </OBR.2>
      <OBR.3> 
          <EI.1>282793</EI.1> 
      </OBR.3> 
      <OBR.4> 
          <CE.1></CE.1> 
          <CE.2>InfectionControl - CPE Contract</CE.2> 
          <CE.3></CE.3> 
      </OBR.4> 
      <OBR.7> 
          <TS.1>20241118143530</TS.1> 
      </OBR.7> 
      <OBR.25></OBR.25> 
    </OBR> 
<REF_I12.RESULTS_NOTES> 
      <OBX> 
        <OBX.1>3</OBX.1> 
        <OBX.2></OBX.2> 
        <OBX.3> 
          <CE.1></CE.1> 
          <CE.2>Yes</CE.2> 
          <CE.3>L</CE.3> 
        </OBX.3> 
        <OBX.5></OBX.5> 
        <OBX.11>F</OBX.11> 
        <OBX.14> 
          <TS.1></TS.1> 
        </OBX.14> 
      </OBX> 
    </REF_I12.RESULTS_NOTES> 
  </REF_I12.OBSERVATION>
<REF_I12.OBSERVATION> 
    <OBR> 
      <OBR.1>4</OBR.1> 
      <OBR.2> 
          <EI.1></EI.1>
	      <EI.2></EI.2>
	      <EI.3></EI.3> 
	      <EI.4></EI.4> 
      </OBR.2>
      <OBR.3> 
          <EI.1>282793</EI.1> 
      </OBR.3> 
      <OBR.4> 
          <CE.1></CE.1> 
          <CE.2>InfectionControl - CRAB</CE.2> 
          <CE.3></CE.3> 
      </OBR.4> 
      <OBR.7> 
          <TS.1>20241118143530</TS.1> 
      </OBR.7> 
      <OBR.25></OBR.25> 
    </OBR> 
<REF_I12.RESULTS_NOTES> 
      <OBX> 
        <OBX.1>4</OBX.1> 
        <OBX.2></OBX.2> 
        <OBX.3> 
          <CE.1></CE.1> 
          <CE.2>Yes</CE.2> 
          <CE.3>L</CE.3> 
        </OBX.3> 
        <OBX.5></OBX.5> 
        <OBX.11>F</OBX.11> 
        <OBX.14> 
          <TS.1></TS.1> 
        </OBX.14> 
      </OBX> 
    </REF_I12.RESULTS_NOTES> 
  </REF_I12.OBSERVATION>
<REF_I12.OBSERVATION> 
    <OBR> 
      <OBR.1>5</OBR.1> 
      <OBR.2> 
          <EI.1></EI.1>
	      <EI.2></EI.2>
	      <EI.3></EI.3> 
	      <EI.4></EI.4> 
      </OBR.2>
      <OBR.3> 
          <EI.1>282793</EI.1> 
      </OBR.3> 
      <OBR.4> 
          <CE.1></CE.1> 
          <CE.2>InfectionControl - CRE</CE.2> 
          <CE.3></CE.3> 
      </OBR.4> 
      <OBR.7> 
          <TS.1>20241118143530</TS.1> 
      </OBR.7> 
      <OBR.25></OBR.25> 
    </OBR> 
<REF_I12.RESULTS_NOTES> 
      <OBX> 
        <OBX.1>5</OBX.1> 
        <OBX.2></OBX.2> 
        <OBX.3> 
          <CE.1></CE.1> 
          <CE.2>Yes</CE.2> 
          <CE.3>L</CE.3> 
        </OBX.3> 
        <OBX.5></OBX.5> 
        <OBX.11>F</OBX.11> 
        <OBX.14> 
          <TS.1></TS.1> 
        </OBX.14> 
      </OBX> 
    </REF_I12.RESULTS_NOTES> 
  </REF_I12.OBSERVATION>
<REF_I12.OBSERVATION> 
    <OBR> 
      <OBR.1>6</OBR.1> 
      <OBR.2> 
          <EI.1></EI.1>
	      <EI.2></EI.2>
	      <EI.3></EI.3> 
	      <EI.4></EI.4> 
      </OBR.2>
      <OBR.3> 
          <EI.1>282793</EI.1> 
      </OBR.3> 
      <OBR.4> 
          <CE.1></CE.1> 
          <CE.2>InfectionControl - ESBL</CE.2> 
          <CE.3></CE.3> 
      </OBR.4> 
      <OBR.7> 
          <TS.1>20241118143530</TS.1> 
      </OBR.7> 
      <OBR.25></OBR.25> 
    </OBR> 
<REF_I12.RESULTS_NOTES> 
      <OBX> 
        <OBX.1>6</OBX.1> 
        <OBX.2></OBX.2> 
        <OBX.3> 
          <CE.1></CE.1> 
          <CE.2>Yes</CE.2> 
          <CE.3>L</CE.3> 
        </OBX.3> 
        <OBX.5></OBX.5> 
        <OBX.11>F</OBX.11> 
        <OBX.14> 
          <TS.1></TS.1> 
        </OBX.14> 
      </OBX> 
    </REF_I12.RESULTS_NOTES> 
  </REF_I12.OBSERVATION>
<REF_I12.OBSERVATION> 
    <OBR> 
      <OBR.1>7</OBR.1> 
      <OBR.2> 
          <EI.1></EI.1>
	      <EI.2></EI.2>
	      <EI.3></EI.3> 
	      <EI.4></EI.4> 
      </OBR.2>
      <OBR.3> 
          <EI.1>282793</EI.1> 
      </OBR.3> 
      <OBR.4> 
          <CE.1></CE.1> 
          <CE.2>InfectionControl - LRVRE</CE.2> 
          <CE.3></CE.3> 
      </OBR.4> 
      <OBR.7> 
          <TS.1>20241118143530</TS.1> 
      </OBR.7> 
      <OBR.25></OBR.25> 
    </OBR> 
<REF_I12.RESULTS_NOTES> 
      <OBX> 
        <OBX.1>7</OBX.1> 
        <OBX.2></OBX.2> 
        <OBX.3> 
          <CE.1></CE.1> 
          <CE.2>Yes</CE.2> 
          <CE.3>L</CE.3> 
        </OBX.3> 
        <OBX.5></OBX.5> 
        <OBX.11>F</OBX.11> 
        <OBX.14> 
          <TS.1></TS.1> 
        </OBX.14> 
      </OBX> 
    </REF_I12.RESULTS_NOTES> 
  </REF_I12.OBSERVATION>
<REF_I12.OBSERVATION> 
    <OBR> 
      <OBR.1>8</OBR.1> 
      <OBR.2> 
          <EI.1></EI.1>
	      <EI.2></EI.2>
	      <EI.3></EI.3> 
	      <EI.4></EI.4> 
      </OBR.2>
      <OBR.3> 
          <EI.1>282793</EI.1> 
      </OBR.3> 
      <OBR.4> 
          <CE.1></CE.1> 
          <CE.2>InfectionControl - MDR Pseudomonas</CE.2> 
          <CE.3></CE.3> 
      </OBR.4> 
      <OBR.7> 
          <TS.1>20241118143530</TS.1> 
      </OBR.7> 
      <OBR.25></OBR.25> 
    </OBR> 
<REF_I12.RESULTS_NOTES> 
      <OBX> 
        <OBX.1>8</OBX.1> 
        <OBX.2></OBX.2> 
        <OBX.3> 
          <CE.1></CE.1> 
          <CE.2>Yes</CE.2> 
          <CE.3>L</CE.3> 
        </OBX.3> 
        <OBX.5></OBX.5> 
        <OBX.11>F</OBX.11> 
        <OBX.14> 
          <TS.1></TS.1> 
        </OBX.14> 
      </OBX> 
    </REF_I12.RESULTS_NOTES> 
  </REF_I12.OBSERVATION>
<REF_I12.OBSERVATION> 
    <OBR> 
      <OBR.1>9</OBR.1> 
      <OBR.2> 
          <EI.1></EI.1>
	      <EI.2></EI.2>
	      <EI.3></EI.3> 
	      <EI.4></EI.4> 
      </OBR.2>
      <OBR.3> 
          <EI.1>282793</EI.1> 
      </OBR.3> 
      <OBR.4> 
          <CE.1></CE.1> 
          <CE.2>InfectionControl - MRSA</CE.2> 
          <CE.3></CE.3> 
      </OBR.4> 
      <OBR.7> 
          <TS.1>20241118143530</TS.1> 
      </OBR.7> 
      <OBR.25></OBR.25> 
    </OBR> 
<REF_I12.RESULTS_NOTES> 
      <OBX> 
        <OBX.1>9</OBX.1> 
        <OBX.2></OBX.2> 
        <OBX.3> 
          <CE.1></CE.1> 
          <CE.2>Yes</CE.2> 
          <CE.3>L</CE.3> 
        </OBX.3> 
        <OBX.5></OBX.5> 
        <OBX.11>F</OBX.11> 
        <OBX.14> 
          <TS.1></TS.1> 
        </OBX.14> 
      </OBX> 
    </REF_I12.RESULTS_NOTES> 
  </REF_I12.OBSERVATION>
<REF_I12.OBSERVATION> 
    <OBR> 
      <OBR.1>10</OBR.1> 
      <OBR.2> 
          <EI.1></EI.1>
	      <EI.2></EI.2>
	      <EI.3></EI.3> 
	      <EI.4></EI.4> 
      </OBR.2>
      <OBR.3> 
          <EI.1>282793</EI.1> 
      </OBR.3> 
      <OBR.4> 
          <CE.1></CE.1> 
          <CE.2>InfectionControl - VRE</CE.2> 
          <CE.3></CE.3> 
      </OBR.4> 
      <OBR.7> 
          <TS.1>20241118143530</TS.1> 
      </OBR.7> 
      <OBR.25></OBR.25> 
    </OBR> 
<REF_I12.RESULTS_NOTES> 
      <OBX> 
        <OBX.1>10</OBX.1> 
        <OBX.2></OBX.2> 
        <OBX.3> 
          <CE.1></CE.1> 
          <CE.2>Yes</CE.2> 
          <CE.3>L</CE.3> 
        </OBX.3> 
        <OBX.5></OBX.5> 
        <OBX.11>F</OBX.11> 
        <OBX.14> 
          <TS.1></TS.1> 
        </OBX.14> 
      </OBX> 
    </REF_I12.RESULTS_NOTES> 
  </REF_I12.OBSERVATION>
<REF_I12.OBSERVATION> 
    <OBR> 
      <OBR.1>11</OBR.1> 
      <OBR.2> 
          <EI.1></EI.1>
	      <EI.2></EI.2>
	      <EI.3></EI.3> 
	      <EI.4></EI.4> 
      </OBR.2>
      <OBR.3> 
          <EI.1>282793</EI.1> 
      </OBR.3> 
      <OBR.4> 
          <CE.1></CE.1> 
          <CE.2>Medications/Nutritional Supplements on Discharge</CE.2> 
          <CE.3></CE.3> 
      </OBR.4> 
      <OBR.7> 
          <TS.1>20241118143530</TS.1> 
      </OBR.7> 
      <OBR.25></OBR.25> 
    </OBR> 
<REF_I12.RESULTS_NOTES> 
      <OBX> 
        <OBX.1>11</OBX.1> 
        <OBX.2>FT</OBX.2> 
        <OBX.3> 
          <CE.1></CE.1> 
          <CE.2>AVANDAMET 2mg/1000mg TABLETS; Qty:1mg; Frequency: ; Direction:1 per day; Route:oral</CE.2> 
          <CE.3>L</CE.3> 
        </OBX.3> 
        <OBX.5></OBX.5> 
        <OBX.11>F</OBX.11> 
        <OBX.14> 
          <TS.1></TS.1> 
        </OBX.14> 
      </OBX> 
    </REF_I12.RESULTS_NOTES> 
  </REF_I12.OBSERVATION>
<REF_I12.OBSERVATION> 
    <OBR> 
      <OBR.1>12</OBR.1> 
      <OBR.2> 
          <EI.1></EI.1>
	      <EI.2></EI.2>
	      <EI.3></EI.3> 
	      <EI.4></EI.4> 
      </OBR.2>
      <OBR.3> 
          <EI.1>282793</EI.1> 
      </OBR.3> 
      <OBR.4> 
          <CE.1></CE.1> 
          <CE.2>Comments</CE.2> 
          <CE.3></CE.3> 
      </OBR.4> 
      <OBR.7> 
          <TS.1>20241118143130</TS.1> 
      </OBR.7> 
      <OBR.25></OBR.25> 
    </OBR> 
<REF_I12.RESULTS_NOTES> 
      <OBX> 
        <OBX.1>12</OBX.1> 
        <OBX.2>FT</OBX.2> 
        <OBX.3> 
          <CE.1></CE.1> 
          <CE.2>some comment</CE.2> 
          <CE.3>L</CE.3> 
        </OBX.3> 
        <OBX.5></OBX.5> 
        <OBX.11>F</OBX.11> 
        <OBX.14> 
          <TS.1></TS.1> 
        </OBX.14> 
      </OBX> 
    </REF_I12.RESULTS_NOTES> 
  </REF_I12.OBSERVATION>
<REF_I12.OBSERVATION> 
    <OBR> 
      <OBR.1>13</OBR.1> 
      <OBR.2> 
          <EI.1></EI.1>
	      <EI.2></EI.2>
	      <EI.3></EI.3> 
	      <EI.4></EI.4> 
      </OBR.2>
      <OBR.3> 
          <EI.1>282793</EI.1> 
      </OBR.3> 
      <OBR.4> 
          <CE.1></CE.1> 
          <CE.2>Comments</CE.2> 
          <CE.3></CE.3> 
      </OBR.4> 
      <OBR.7> 
          <TS.1>20241118143530</TS.1> 
      </OBR.7> 
      <OBR.25></OBR.25> 
    </OBR> 
<REF_I12.RESULTS_NOTES> 
      <OBX> 
        <OBX.1>13</OBX.1> 
        <OBX.2>FT</OBX.2> 
        <OBX.3> 
          <CE.1></CE.1> 
          <CE.2>FENTANYL 1200microgram LOZENGES; Qty:2mg; Frequency: ; Direction:2 per day; Route:oral</CE.2> 
          <CE.3>L</CE.3> 
        </OBX.3> 
        <OBX.5></OBX.5> 
        <OBX.11>F</OBX.11> 
        <OBX.14> 
          <TS.1></TS.1> 
        </OBX.14> 
      </OBX> 
    </REF_I12.RESULTS_NOTES> 
  </REF_I12.OBSERVATION>
<REF_I12.OBSERVATION> 
    <OBR> 
      <OBR.1>14</OBR.1> 
      <OBR.2> 
          <EI.1></EI.1>
	      <EI.2></EI.2>
	      <EI.3></EI.3> 
	      <EI.4></EI.4> 
      </OBR.2>
      <OBR.3> 
          <EI.1>282793</EI.1> 
      </OBR.3> 
      <OBR.4> 
          <CE.1></CE.1> 
          <CE.2>Comments</CE.2> 
          <CE.3></CE.3> 
      </OBR.4> 
      <OBR.7> 
          <TS.1>20241118143208</TS.1> 
      </OBR.7> 
      <OBR.25></OBR.25> 
    </OBR> 
<REF_I12.RESULTS_NOTES> 
      <OBX> 
        <OBX.1>14</OBX.1> 
        <OBX.2>FT</OBX.2> 
        <OBX.3> 
          <CE.1></CE.1> 
          <CE.2>some other comment</CE.2> 
          <CE.3>L</CE.3> 
        </OBX.3> 
        <OBX.5></OBX.5> 
        <OBX.11>F</OBX.11> 
        <OBX.14> 
          <TS.1></TS.1> 
        </OBX.14> 
      </OBX> 
    </REF_I12.RESULTS_NOTES> 
  </REF_I12.OBSERVATION>
<REF_I12.OBSERVATION> 
    <OBR> 
      <OBR.1>15</OBR.1> 
      <OBR.2> 
          <EI.1></EI.1>
	      <EI.2></EI.2>
	      <EI.3></EI.3> 
	      <EI.4></EI.4> 
      </OBR.2>
      <OBR.3> 
          <EI.1>282793</EI.1> 
      </OBR.3> 
      <OBR.4> 
          <CE.1></CE.1> 
          <CE.2>Additional Medication Comments</CE.2> 
          <CE.3></CE.3> 
      </OBR.4> 
      <OBR.7> 
          <TS.1>20241118143528</TS.1> 
      </OBR.7> 
      <OBR.25></OBR.25> 
    </OBR> 
<REF_I12.RESULTS_NOTES> 
      <OBX> 
        <OBX.1>15</OBX.1> 
        <OBX.2>FT</OBX.2> 
        <OBX.3> 
          <CE.1></CE.1> 
          <CE.2>Additional Medications/Nutritional Supplements (Free Text) cb test</CE.2> 
          <CE.3>L</CE.3> 
        </OBX.3> 
        <OBX.5></OBX.5> 
        <OBX.11>F</OBX.11> 
        <OBX.14> 
          <TS.1></TS.1> 
        </OBX.14> 
      </OBX> 
    </REF_I12.RESULTS_NOTES> 
  </REF_I12.OBSERVATION>
<REF_I12.OBSERVATION> 
    <OBR> 
      <OBR.1>16</OBR.1> 
      <OBR.2> 
          <EI.1></EI.1>
	      <EI.2></EI.2>
	      <EI.3></EI.3> 
	      <EI.4></EI.4> 
      </OBR.2>
      <OBR.3> 
          <EI.1>282793</EI.1> 
      </OBR.3> 
      <OBR.4> 
          <CE.1></CE.1> 
          <CE.2>Discontinued Medications/Nutritional Supplements</CE.2> 
          <CE.3></CE.3> 
      </OBR.4> 
      <OBR.7> 
          <TS.1>20241118143238</TS.1> 
      </OBR.7> 
      <OBR.25></OBR.25> 
    </OBR> 
<REF_I12.RESULTS_NOTES> 
      <OBX> 
        <OBX.1>16</OBX.1> 
        <OBX.2>FT</OBX.2> 
        <OBX.3> 
          <CE.1></CE.1> 
          <CE.2>ACICLOVIR 1000mg/40mL INJECTION</CE.2> 
          <CE.3>L</CE.3> 
        </OBX.3> 
        <OBX.5></OBX.5> 
        <OBX.11>F</OBX.11> 
        <OBX.14> 
          <TS.1></TS.1> 
        </OBX.14> 
      </OBX> 
    </REF_I12.RESULTS_NOTES> 
  </REF_I12.OBSERVATION>
<REF_I12.OBSERVATION> 
    <OBR> 
      <OBR.1>17</OBR.1> 
      <OBR.2> 
          <EI.1></EI.1>
	      <EI.2></EI.2>
	      <EI.3></EI.3> 
	      <EI.4></EI.4> 
      </OBR.2>
      <OBR.3> 
          <EI.1>282793</EI.1> 
      </OBR.3> 
      <OBR.4> 
          <CE.1></CE.1> 
          <CE.2>Discontinued Medications Comments</CE.2> 
          <CE.3></CE.3> 
      </OBR.4> 
      <OBR.7> 
          <TS.1>20241118143238</TS.1> 
      </OBR.7> 
      <OBR.25></OBR.25> 
    </OBR> 
<REF_I12.RESULTS_NOTES> 
      <OBX> 
        <OBX.1>17</OBX.1> 
        <OBX.2>FT</OBX.2> 
        <OBX.3> 
          <CE.1></CE.1> 
          <CE.2>discontinues med 1 cb test</CE.2> 
          <CE.3>L</CE.3> 
        </OBX.3> 
        <OBX.5></OBX.5> 
        <OBX.11>F</OBX.11> 
        <OBX.14> 
          <TS.1></TS.1> 
        </OBX.14> 
      </OBX> 
    </REF_I12.RESULTS_NOTES> 
  </REF_I12.OBSERVATION>
<REF_I12.OBSERVATION> 
    <OBR> 
      <OBR.1>18</OBR.1> 
      <OBR.2> 
          <EI.1></EI.1>
	      <EI.2></EI.2>
	      <EI.3></EI.3> 
	      <EI.4></EI.4> 
      </OBR.2>
      <OBR.3> 
          <EI.1>282793</EI.1> 
      </OBR.3> 
      <OBR.4> 
          <CE.1></CE.1> 
          <CE.2>Discontinued Medications/Nutritional Supplements</CE.2> 
          <CE.3></CE.3> 
      </OBR.4> 
      <OBR.7> 
          <TS.1>20241118143259</TS.1> 
      </OBR.7> 
      <OBR.25></OBR.25> 
    </OBR> 
<REF_I12.RESULTS_NOTES> 
      <OBX> 
        <OBX.1>18</OBX.1> 
        <OBX.2>FT</OBX.2> 
        <OBX.3> 
          <CE.1></CE.1> 
          <CE.2>MICONAZOLE 1200mg OVULE</CE.2> 
          <CE.3>L</CE.3> 
        </OBX.3> 
        <OBX.5></OBX.5> 
        <OBX.11>F</OBX.11> 
        <OBX.14> 
          <TS.1></TS.1> 
        </OBX.14> 
      </OBX> 
    </REF_I12.RESULTS_NOTES> 
  </REF_I12.OBSERVATION>
<REF_I12.OBSERVATION> 
    <OBR> 
      <OBR.1>19</OBR.1> 
      <OBR.2> 
          <EI.1></EI.1>
	      <EI.2></EI.2>
	      <EI.3></EI.3> 
	      <EI.4></EI.4> 
      </OBR.2>
      <OBR.3> 
          <EI.1>282793</EI.1> 
      </OBR.3> 
      <OBR.4> 
          <CE.1></CE.1> 
          <CE.2>Discontinued Medications Comments</CE.2> 
          <CE.3></CE.3> 
      </OBR.4> 
      <OBR.7> 
          <TS.1>20241118143259</TS.1> 
      </OBR.7> 
      <OBR.25></OBR.25> 
    </OBR> 
<REF_I12.RESULTS_NOTES> 
      <OBX> 
        <OBX.1>19</OBX.1> 
        <OBX.2>FT</OBX.2> 
        <OBX.3> 
          <CE.1></CE.1> 
          <CE.2>discont med 2 cb tesst</CE.2> 
          <CE.3>L</CE.3> 
        </OBX.3> 
        <OBX.5></OBX.5> 
        <OBX.11>F</OBX.11> 
        <OBX.14> 
          <TS.1></TS.1> 
        </OBX.14> 
      </OBX> 
    </REF_I12.RESULTS_NOTES> 
  </REF_I12.OBSERVATION>
<REF_I12.OBSERVATION> 
    <OBR> 
      <OBR.1>20</OBR.1> 
      <OBR.2> 
          <EI.1></EI.1>
	      <EI.2></EI.2>
	      <EI.3></EI.3> 
	      <EI.4></EI.4> 
      </OBR.2>
      <OBR.3> 
          <EI.1>282793</EI.1> 
      </OBR.3> 
      <OBR.4> 
          <CE.1></CE.1> 
          <CE.2>Additional Discontinued Medication Comments</CE.2> 
          <CE.3></CE.3> 
      </OBR.4> 
      <OBR.7> 
          <TS.1>20241118143528</TS.1> 
      </OBR.7> 
      <OBR.25></OBR.25> 
    </OBR> 
<REF_I12.RESULTS_NOTES> 
      <OBX> 
        <OBX.1>20</OBX.1> 
        <OBX.2>FT</OBX.2> 
        <OBX.3> 
          <CE.1></CE.1> 
          <CE.2>Additional Discontinued Medications/Nutritional supplements (Free Text) cb test</CE.2> 
          <CE.3>L</CE.3> 
        </OBX.3> 
        <OBX.5></OBX.5> 
        <OBX.11>F</OBX.11> 
        <OBX.14> 
          <TS.1></TS.1> 
        </OBX.14> 
      </OBX> 
    </REF_I12.RESULTS_NOTES> 
  </REF_I12.OBSERVATION>
<REF_I12.OBSERVATION> 
    <OBR> 
      <OBR.1>21</OBR.1> 
      <OBR.2> 
          <EI.1></EI.1>
	      <EI.2></EI.2>
	      <EI.3></EI.3> 
	      <EI.4></EI.4> 
      </OBR.2>
      <OBR.3> 
          <EI.1>282793</EI.1> 
      </OBR.3> 
      <OBR.4> 
          <CE.1></CE.1> 
          <CE.2>Pertinent Clinical Information (Free Text)</CE.2> 
          <CE.3></CE.3> 
      </OBR.4> 
      <OBR.7> 
          <TS.1>20241118143530</TS.1> 
      </OBR.7> 
      <OBR.25></OBR.25> 
    </OBR> 
<REF_I12.RESULTS_NOTES> 
      <OBX> 
        <OBX.1>21</OBX.1> 
        <OBX.2>FT</OBX.2> 
        <OBX.3> 
          <CE.1></CE.1> 
          <CE.2>Pertinent Clinical Information (Free Text) cb test</CE.2> 
          <CE.3>L</CE.3> 
        </OBX.3> 
        <OBX.5></OBX.5> 
        <OBX.11>F</OBX.11> 
        <OBX.14> 
          <TS.1></TS.1> 
        </OBX.14> 
      </OBX> 
    </REF_I12.RESULTS_NOTES> 
  </REF_I12.OBSERVATION>
<REF_I12.OBSERVATION> 
    <OBR> 
      <OBR.1>22</OBR.1> 
      <OBR.2> 
          <EI.1></EI.1>
	      <EI.2></EI.2>
	      <EI.3></EI.3> 
	      <EI.4></EI.4> 
      </OBR.2>
      <OBR.3> 
          <EI.1>282793</EI.1> 
      </OBR.3> 
      <OBR.4> 
          <CE.1></CE.1> 
          <CE.2>Other Recommendations on Discharge Chemotherapy(planned future care)(Free Text)</CE.2> 
          <CE.3></CE.3> 
      </OBR.4> 
      <OBR.7> 
          <TS.1>20241118143530</TS.1> 
      </OBR.7> 
      <OBR.25></OBR.25> 
    </OBR> 
<REF_I12.RESULTS_NOTES> 
      <OBX> 
        <OBX.1>22</OBX.1> 
        <OBX.2>FT</OBX.2> 
        <OBX.3> 
          <CE.1></CE.1> 
          <CE.2>other recommnedations on discharge chemotherapy (planned future care) (free text) cb test</CE.2> 
          <CE.3>L</CE.3> 
        </OBX.3> 
        <OBX.5></OBX.5> 
        <OBX.11>F</OBX.11> 
        <OBX.14> 
          <TS.1></TS.1> 
        </OBX.14> 
      </OBX> 
    </REF_I12.RESULTS_NOTES> 
  </REF_I12.OBSERVATION>
<REF_I12.OBSERVATION> 
    <OBR> 
      <OBR.1>23</OBR.1> 
      <OBR.2> 
          <EI.1></EI.1>
	      <EI.2></EI.2>
	      <EI.3></EI.3> 
	      <EI.4></EI.4> 
      </OBR.2>
      <OBR.3> 
          <EI.1>282793</EI.1> 
      </OBR.3> 
      <OBR.4> 
          <CE.1></CE.1> 
          <CE.2>Discharge Circumstances</CE.2> 
          <CE.3></CE.3> 
      </OBR.4> 
      <OBR.7> 
          <TS.1>20241118143530</TS.1> 
      </OBR.7> 
      <OBR.25></OBR.25> 
    </OBR> 
<REF_I12.RESULTS_NOTES> 
      <OBX> 
        <OBX.1>23</OBX.1> 
        <OBX.2>FT</OBX.2> 
        <OBX.3> 
          <CE.1></CE.1> 
          <CE.2>Discharge Circumstances (Free Text) cb test</CE.2> 
          <CE.3>L</CE.3> 
        </OBX.3> 
        <OBX.5></OBX.5> 
        <OBX.11>F</OBX.11> 
        <OBX.14> 
          <TS.1></TS.1> 
        </OBX.14> 
      </OBX> 
    </REF_I12.RESULTS_NOTES> 
  </REF_I12.OBSERVATION>
<REF_I12.OBSERVATION> 
    <OBR> 
      <OBR.1>24</OBR.1> 
      <OBR.2> 
          <EI.1></EI.1>
	      <EI.2></EI.2>
	      <EI.3></EI.3> 
	      <EI.4></EI.4> 
      </OBR.2>
      <OBR.3> 
          <EI.1>282793</EI.1> 
      </OBR.3> 
      <OBR.4> 
          <CE.1></CE.1> 
          <CE.2>Functional Status</CE.2> 
          <CE.3></CE.3> 
      </OBR.4> 
      <OBR.7> 
          <TS.1>20241118143530</TS.1> 
      </OBR.7> 
      <OBR.25></OBR.25> 
    </OBR> 
<REF_I12.RESULTS_NOTES> 
      <OBX> 
        <OBX.1>24</OBX.1> 
        <OBX.2>FT</OBX.2> 
        <OBX.3> 
          <CE.1></CE.1> 
          <CE.2>Functional Status (Free Text) cb test</CE.2> 
          <CE.3>L</CE.3> 
        </OBX.3> 
        <OBX.5></OBX.5> 
        <OBX.11>F</OBX.11> 
        <OBX.14> 
          <TS.1></TS.1> 
        </OBX.14> 
      </OBX> 
    </REF_I12.RESULTS_NOTES> 
  </REF_I12.OBSERVATION>
<REF_I12.OBSERVATION> 
    <OBR> 
      <OBR.1>25</OBR.1> 
      <OBR.2> 
          <EI.1></EI.1>
	      <EI.2></EI.2>
	      <EI.3></EI.3> 
	      <EI.4></EI.4> 
      </OBR.2>
      <OBR.3> 
          <EI.1>282793</EI.1> 
      </OBR.3> 
      <OBR.4> 
          <CE.1></CE.1> 
          <CE.2>Communication/Education given to ParentFamily/Carer</CE.2> 
          <CE.3></CE.3> 
      </OBR.4> 
      <OBR.7> 
          <TS.1>20241118143530</TS.1> 
      </OBR.7> 
      <OBR.25></OBR.25> 
    </OBR> 
<REF_I12.RESULTS_NOTES> 
      <OBX> 
        <OBX.1>25</OBX.1> 
        <OBX.2>FT</OBX.2> 
        <OBX.3> 
          <CE.1></CE.1> 
          <CE.2>Communication/Education given to Patient/Family/Carer (Free Text) cb test</CE.2> 
          <CE.3>L</CE.3> 
        </OBX.3> 
        <OBX.5></OBX.5> 
        <OBX.11>F</OBX.11> 
        <OBX.14> 
          <TS.1></TS.1> 
        </OBX.14> 
      </OBX> 
    </REF_I12.RESULTS_NOTES> 
  </REF_I12.OBSERVATION>
<REF_I12.OBSERVATION> 
    <OBR> 
      <OBR.1>26</OBR.1> 
      <OBR.2> 
          <EI.1></EI.1>
	      <EI.2></EI.2>
	      <EI.3></EI.3> 
	      <EI.4></EI.4> 
      </OBR.2>
      <OBR.3> 
          <EI.1>282793</EI.1> 
      </OBR.3> 
      <OBR.4> 
          <CE.1></CE.1> 
          <CE.2>Follow Up Plans (Free Text)</CE.2> 
          <CE.3></CE.3> 
      </OBR.4> 
      <OBR.7> 
          <TS.1>20241118143530</TS.1> 
      </OBR.7> 
      <OBR.25></OBR.25> 
    </OBR> 
<REF_I12.RESULTS_NOTES> 
      <OBX> 
        <OBX.1>26</OBX.1> 
        <OBX.2>FT</OBX.2> 
        <OBX.3> 
          <CE.1></CE.1> 
          <CE.2>Follow up plans (Free Text)  cb test</CE.2> 
          <CE.3>L</CE.3> 
        </OBX.3> 
        <OBX.5></OBX.5> 
        <OBX.11>F</OBX.11> 
        <OBX.14> 
          <TS.1></TS.1> 
        </OBX.14> 
      </OBX> 
    </REF_I12.RESULTS_NOTES> 
  </REF_I12.OBSERVATION>
<REF_I12.OBSERVATION> 
    <OBR> 
      <OBR.1>27</OBR.1> 
      <OBR.2> 
          <EI.1></EI.1>
	      <EI.2></EI.2>
	      <EI.3></EI.3> 
	      <EI.4></EI.4> 
      </OBR.2>
      <OBR.3> 
          <EI.1>282793</EI.1> 
      </OBR.3> 
      <OBR.4> 
          <CE.1></CE.1> 
          <CE.2>Date of Discharge</CE.2> 
          <CE.3></CE.3> 
      </OBR.4> 
      <OBR.7> 
          <TS.1>20241118143530</TS.1> 
      </OBR.7> 
      <OBR.25></OBR.25> 
    </OBR> 
<REF_I12.RESULTS_NOTES> 
      <OBX> 
        <OBX.1>27</OBX.1> 
        <OBX.2>NM</OBX.2> 
        <OBX.3> 
          <CE.1></CE.1> 
          <CE.2>25/10/2022 00:00:00</CE.2> 
          <CE.3>L</CE.3> 
        </OBX.3> 
        <OBX.5></OBX.5> 
        <OBX.11>F</OBX.11> 
        <OBX.14> 
          <TS.1></TS.1> 
        </OBX.14> 
      </OBX> 
    </REF_I12.RESULTS_NOTES> 
  </REF_I12.OBSERVATION>
<REF_I12.OBSERVATION> 
    <OBR> 
      <OBR.1>28</OBR.1> 
      <OBR.2> 
          <EI.1></EI.1>
	      <EI.2></EI.2>
	      <EI.3></EI.3> 
	      <EI.4></EI.4> 
      </OBR.2>
      <OBR.3> 
          <EI.1>282793</EI.1> 
      </OBR.3> 
      <OBR.4> 
          <CE.1></CE.1> 
          <CE.2>Validated By</CE.2> 
          <CE.3></CE.3> 
      </OBR.4> 
      <OBR.7> 
          <TS.1>20241118143530</TS.1> 
      </OBR.7> 
      <OBR.25></OBR.25> 
    </OBR> 
<REF_I12.RESULTS_NOTES> 
      <OBX> 
        <OBX.1>28</OBX.1> 
        <OBX.2>FT</OBX.2> 
        <OBX.3> 
          <CE.1></CE.1> 
          <CE.2>dev dmf (DMF)</CE.2> 
          <CE.3>L</CE.3> 
        </OBX.3> 
        <OBX.5></OBX.5> 
        <OBX.11>F</OBX.11> 
        <OBX.14> 
          <TS.1></TS.1> 
        </OBX.14> 
      </OBX> 
    </REF_I12.RESULTS_NOTES> 
  </REF_I12.OBSERVATION>
<REF_I12.OBSERVATION> 
    <OBR> 
      <OBR.1>29</OBR.1> 
      <OBR.2> 
          <EI.1></EI.1>
	      <EI.2></EI.2>
	      <EI.3></EI.3> 
	      <EI.4></EI.4> 
      </OBR.2>
      <OBR.3> 
          <EI.1>282793</EI.1> 
      </OBR.3> 
      <OBR.4> 
          <CE.1></CE.1> 
          <CE.2>Letter Approval Date</CE.2> 
          <CE.3></CE.3> 
      </OBR.4> 
      <OBR.7> 
          <TS.1>20241118143530</TS.1> 
      </OBR.7> 
      <OBR.25></OBR.25> 
    </OBR> 
<REF_I12.RESULTS_NOTES> 
      <OBX> 
        <OBX.1>29</OBX.1> 
        <OBX.2>FT</OBX.2> 
        <OBX.3> 
          <CE.1></CE.1> 
          <CE.2>18/11/2024 14:35:30</CE.2> 
          <CE.3>L</CE.3> 
        </OBX.3> 
        <OBX.5></OBX.5> 
        <OBX.11>F</OBX.11> 
        <OBX.14> 
          <TS.1></TS.1> 
        </OBX.14> 
      </OBX> 
    </REF_I12.RESULTS_NOTES> 
  </REF_I12.OBSERVATION>
<REF_I12.PATIENT_VISIT> 
    <PV1> 
      <PV1.2>I</PV1.2> 
      <PV1.3> 
        <PL.9>SVUH</PL.9> 
      </PV1.3> 
      <PV1.4></PV1.4>
      <PV1.7> 
        <XCN.1></XCN.1> 
        <XCN.2> 
          <FN.1>Hlink</FN.1> 
        </XCN.2> 
        <XCN.3>Doctor</XCN.3>
        <XCN.6>DR.</XCN.6> 
      </PV1.7> 
      <PV1.9> 
        <XCN.1></XCN.1> 
        <XCN.2>
          <FN.1>HURLEY</FN.1> 
        </XCN.2> 
        <XCN.3>HILARY</XCN.3> 
        <XCN.6>DR</XCN.6> 
      </PV1.9> 
      <PV1.14>9</PV1.14>
      <PV1.36>01</PV1.36> 
      <PV1.44> 
        <TS.1>20221024</TS.1>
      </PV1.44> 
      <PV1.45> 
        <TS.1>20221025000000</TS.1>
      </PV1.45> 
    </PV1> 
  </REF_I12.PATIENT_VISIT>
</REF_I12>